rsapi/__init__.py
rsapi/osrs.py
rsapi/test_osrs.py
rsapi/util.py
rsapi/wiki.py
rsapi-0.0.42.dist-info/METADATA
rsapi-0.0.42.dist-info/WHEEL
rsapi-0.0.42.dist-info/top_level.txt
rsapi-0.0.42.dist-info/RECORD
